{
"meta":{"test_sets":[],"test_metrics":[],"learn_metrics":[{"best_value":"Min","name":"Logloss"}],"launch_mode":"Train","parameters":"","iteration_count":500,"learn_sets":["learn"],"name":"experiment"},
"iterations":[
{"learn":[0.6890474286],"iteration":0,"passed_time":0.001811028911,"remaining_time":0.9037034265},
{"learn":[0.6872821237],"iteration":1,"passed_time":0.003383960762,"remaining_time":0.8426062297},
{"learn":[0.6853479204],"iteration":2,"passed_time":0.004653553129,"remaining_time":0.7709386351},
{"learn":[0.6828845765],"iteration":3,"passed_time":0.006262446661,"remaining_time":0.776543386},
{"learn":[0.6805491968],"iteration":4,"passed_time":0.00810413725,"remaining_time":0.8023095878},
{"learn":[0.6775800298],"iteration":5,"passed_time":0.009491397729,"remaining_time":0.781458413},
{"learn":[0.6754260201],"iteration":6,"passed_time":0.0107404148,"remaining_time":0.7564320711},
{"learn":[0.6732984003],"iteration":7,"passed_time":0.01201116592,"remaining_time":0.7386867038},
{"learn":[0.6715845574],"iteration":8,"passed_time":0.01325013717,"remaining_time":0.7228685944},
{"learn":[0.6703757221],"iteration":9,"passed_time":0.0144552932,"remaining_time":0.7083093666},
{"learn":[0.6673048861],"iteration":10,"passed_time":0.01566965873,"remaining_time":0.6965875565},
{"learn":[0.6656949895],"iteration":11,"passed_time":0.01686084936,"remaining_time":0.6856745405},
{"learn":[0.6628905434],"iteration":12,"passed_time":0.01807681699,"remaining_time":0.6771853748},
{"learn":[0.6601650222],"iteration":13,"passed_time":0.01933335079,"remaining_time":0.6711434633},
{"learn":[0.6582559565],"iteration":14,"passed_time":0.02054576158,"remaining_time":0.6643129577},
{"learn":[0.6557789503],"iteration":15,"passed_time":0.02176342199,"remaining_time":0.658343515},
{"learn":[0.6538541885],"iteration":16,"passed_time":0.02299442308,"remaining_time":0.6533121381},
{"learn":[0.6523580175],"iteration":17,"passed_time":0.0241980677,"remaining_time":0.6479704796},
{"learn":[0.6503867748],"iteration":18,"passed_time":0.02544404181,"remaining_time":0.6441360058},
{"learn":[0.6479412354],"iteration":19,"passed_time":0.02664938928,"remaining_time":0.6395853428},
{"learn":[0.6466775341],"iteration":20,"passed_time":0.02783994511,"remaining_time":0.6350158909},
{"learn":[0.6449740767],"iteration":21,"passed_time":0.0290550059,"remaining_time":0.6312860373},
{"learn":[0.6433866336],"iteration":22,"passed_time":0.03025257466,"remaining_time":0.6274120919},
{"learn":[0.6414629364],"iteration":23,"passed_time":0.03145367004,"remaining_time":0.6238311225},
{"learn":[0.6405476147],"iteration":24,"passed_time":0.03269715537,"remaining_time":0.6212459519},
{"learn":[0.6390869024],"iteration":25,"passed_time":0.0339193903,"remaining_time":0.618376577},
{"learn":[0.6370589033],"iteration":26,"passed_time":0.0351209794,"remaining_time":0.6152675281},
{"learn":[0.6351270207],"iteration":27,"passed_time":0.0363219438,"remaining_time":0.6122841954},
{"learn":[0.6336341426],"iteration":28,"passed_time":0.0375698122,"remaining_time":0.6101855706},
{"learn":[0.6321832177],"iteration":29,"passed_time":0.03880884391,"remaining_time":0.6080052212},
{"learn":[0.6306943061],"iteration":30,"passed_time":0.04006951897,"remaining_time":0.6062130451},
{"learn":[0.6290611114],"iteration":31,"passed_time":0.04148847328,"remaining_time":0.6067689217},
{"learn":[0.6275712691],"iteration":32,"passed_time":0.04279726148,"remaining_time":0.6056460943},
{"learn":[0.6265646583],"iteration":33,"passed_time":0.04405701962,"remaining_time":0.6038403278},
{"learn":[0.6249896894],"iteration":34,"passed_time":0.04536826173,"remaining_time":0.602749763},
{"learn":[0.6241564121],"iteration":35,"passed_time":0.04662451341,"remaining_time":0.6009381728},
{"learn":[0.6226103731],"iteration":36,"passed_time":0.04784662743,"remaining_time":0.5987294189},
{"learn":[0.6217648129],"iteration":37,"passed_time":0.04907232852,"remaining_time":0.5966162047},
{"learn":[0.6207705192],"iteration":38,"passed_time":0.05034248515,"remaining_time":0.5950739911},
{"learn":[0.619915774],"iteration":39,"passed_time":0.05159575432,"remaining_time":0.5933511746},
{"learn":[0.6183340387],"iteration":40,"passed_time":0.05287377026,"remaining_time":0.5919283061},
{"learn":[0.6173051079],"iteration":41,"passed_time":0.05408679569,"remaining_time":0.5898036291},
{"learn":[0.616429925],"iteration":42,"passed_time":0.05532505154,"remaining_time":0.5879895012},
{"learn":[0.6155606348],"iteration":43,"passed_time":0.05656835549,"remaining_time":0.586253866},
{"learn":[0.6146875998],"iteration":44,"passed_time":0.05781234462,"remaining_time":0.58454704},
{"learn":[0.6140361762],"iteration":45,"passed_time":0.05909514668,"remaining_time":0.5832434042},
{"learn":[0.6127812811],"iteration":46,"passed_time":0.06035381661,"remaining_time":0.5817080623},
{"learn":[0.6121314016],"iteration":47,"passed_time":0.06162154491,"remaining_time":0.5802695479},
{"learn":[0.6112440764],"iteration":48,"passed_time":0.06300067402,"remaining_time":0.5798633466},
{"learn":[0.6100137273],"iteration":49,"passed_time":0.06429215157,"remaining_time":0.5786293641},
{"learn":[0.6085543834],"iteration":50,"passed_time":0.06570895502,"remaining_time":0.5784964864},
{"learn":[0.607852521],"iteration":51,"passed_time":0.06697639112,"remaining_time":0.5770273696},
{"learn":[0.6066784863],"iteration":52,"passed_time":0.06820717054,"remaining_time":0.5752567025},
{"learn":[0.6059306356],"iteration":53,"passed_time":0.06941338455,"remaining_time":0.5733031391},
{"learn":[0.6049361989],"iteration":54,"passed_time":0.07069452408,"remaining_time":0.5719829675},
{"learn":[0.6043676971],"iteration":55,"passed_time":0.07202516723,"remaining_time":0.571056683},
{"learn":[0.6031280314],"iteration":56,"passed_time":0.0733245444,"remaining_time":0.5698732135},
{"learn":[0.6024143852],"iteration":57,"passed_time":0.07456127877,"remaining_time":0.5682083658},
{"learn":[0.6016423086],"iteration":58,"passed_time":0.07590757003,"remaining_time":0.5673769217},
{"learn":[0.6006143645],"iteration":59,"passed_time":0.07720504774,"remaining_time":0.5661703501},
{"learn":[0.599503597],"iteration":60,"passed_time":0.07850773502,"remaining_time":0.5649982897},
{"learn":[0.5986879059],"iteration":61,"passed_time":0.07978312112,"remaining_time":0.5636291459},
{"learn":[0.598023515],"iteration":62,"passed_time":0.08105236082,"remaining_time":0.5622203441},
{"learn":[0.5974729712],"iteration":63,"passed_time":0.08235243324,"remaining_time":0.5610259515},
{"learn":[0.5966152681],"iteration":64,"passed_time":0.08363223265,"remaining_time":0.5596926339},
{"learn":[0.5956499833],"iteration":65,"passed_time":0.08492372621,"remaining_time":0.558437836},
{"learn":[0.5950250831],"iteration":66,"passed_time":0.08624576442,"remaining_time":0.5573793432},
{"learn":[0.5942199654],"iteration":67,"passed_time":0.08753765509,"remaining_time":0.5561215735},
{"learn":[0.5936394651],"iteration":68,"passed_time":0.08894845813,"remaining_time":0.5556055863},
{"learn":[0.5930625652],"iteration":69,"passed_time":0.09051529397,"remaining_time":0.5560225201},
{"learn":[0.5923066151],"iteration":70,"passed_time":0.09184280347,"remaining_time":0.5549375027},
{"learn":[0.5912323702],"iteration":71,"passed_time":0.09367798002,"remaining_time":0.5568635479},
{"learn":[0.5904976997],"iteration":72,"passed_time":0.09507243506,"remaining_time":0.556108627},
{"learn":[0.5900207558],"iteration":73,"passed_time":0.09653733279,"remaining_time":0.5557419428},
{"learn":[0.5895532647],"iteration":74,"passed_time":0.09782214878,"remaining_time":0.5543255098},
{"learn":[0.5887259696],"iteration":75,"passed_time":0.09928129697,"remaining_time":0.5538851305},
{"learn":[0.5884684064],"iteration":76,"passed_time":0.1007457196,"remaining_time":0.5534472647},
{"learn":[0.5877729417],"iteration":77,"passed_time":0.1019780205,"remaining_time":0.551727239},
{"learn":[0.5872135621],"iteration":78,"passed_time":0.1032377484,"remaining_time":0.5501657225},
{"learn":[0.5867535656],"iteration":79,"passed_time":0.10457083,"remaining_time":0.5489968573},
{"learn":[0.5862212252],"iteration":80,"passed_time":0.1062011695,"remaining_time":0.549361605},
{"learn":[0.5854729549],"iteration":81,"passed_time":0.1075750993,"remaining_time":0.5483706283},
{"learn":[0.5846979219],"iteration":82,"passed_time":0.1088292753,"remaining_time":0.5467687689},
{"learn":[0.5839687129],"iteration":83,"passed_time":0.1102035181,"remaining_time":0.5457698038},
{"learn":[0.5833659363],"iteration":84,"passed_time":0.1115367503,"remaining_time":0.5445617807},
{"learn":[0.5828067105],"iteration":85,"passed_time":0.1128795459,"remaining_time":0.5433968838},
{"learn":[0.582175975],"iteration":86,"passed_time":0.1141453194,"remaining_time":0.5418622636},
{"learn":[0.5816800814],"iteration":87,"passed_time":0.1154136624,"remaining_time":0.540345783},
{"learn":[0.5809507123],"iteration":88,"passed_time":0.1166615006,"remaining_time":0.538740188},
{"learn":[0.5799579984],"iteration":89,"passed_time":0.1179053788,"remaining_time":0.5371245036},
{"learn":[0.5793311624],"iteration":90,"passed_time":0.1192746327,"remaining_time":0.5360804918},
{"learn":[0.5789693871],"iteration":91,"passed_time":0.1205541701,"remaining_time":0.5346315369},
{"learn":[0.5784027234],"iteration":92,"passed_time":0.1218505748,"remaining_time":0.5332600425},
{"learn":[0.5775491571],"iteration":93,"passed_time":0.1232194269,"remaining_time":0.5322030565},
{"learn":[0.5769202934],"iteration":94,"passed_time":0.1244508008,"remaining_time":0.5305534138},
{"learn":[0.5766173137],"iteration":95,"passed_time":0.1257947849,"remaining_time":0.5293863864},
{"learn":[0.5761823167],"iteration":96,"passed_time":0.1273316491,"remaining_time":0.5290170577},
{"learn":[0.5757797427],"iteration":97,"passed_time":0.1286276004,"remaining_time":0.5276356671},
{"learn":[0.5750923738],"iteration":98,"passed_time":0.1299595132,"remaining_time":0.5264016645},
{"learn":[0.5740725489],"iteration":99,"passed_time":0.1317218647,"remaining_time":0.5268874588},
{"learn":[0.5731740826],"iteration":100,"passed_time":0.1333176891,"remaining_time":0.5266708707},
{"learn":[0.5728466658],"iteration":101,"passed_time":0.1346960121,"remaining_time":0.525578557},
{"learn":[0.572321918],"iteration":102,"passed_time":0.136083726,"remaining_time":0.5245168856},
{"learn":[0.5719601825],"iteration":103,"passed_time":0.1375920414,"remaining_time":0.5239081577},
{"learn":[0.5713825078],"iteration":104,"passed_time":0.1390295297,"remaining_time":0.5230158499},
{"learn":[0.570977573],"iteration":105,"passed_time":0.1404450636,"remaining_time":0.5220316515},
{"learn":[0.5704991195],"iteration":106,"passed_time":0.1418104994,"remaining_time":0.5208553855},
{"learn":[0.5700763791],"iteration":107,"passed_time":0.1431165365,"remaining_time":0.5194600215},
{"learn":[0.5695303345],"iteration":108,"passed_time":0.1446330428,"remaining_time":0.5188212818},
{"learn":[0.5688641068],"iteration":109,"passed_time":0.1461950721,"remaining_time":0.5183279828},
{"learn":[0.5684807094],"iteration":110,"passed_time":0.1475899299,"remaining_time":0.5172295741},
{"learn":[0.5682377162],"iteration":111,"passed_time":0.1489630736,"remaining_time":0.5160506477},
{"learn":[0.5675328191],"iteration":112,"passed_time":0.1503769852,"remaining_time":0.515007905},
{"learn":[0.5667941149],"iteration":113,"passed_time":0.151844844,"remaining_time":0.5141413139},
{"learn":[0.5662428815],"iteration":114,"passed_time":0.1532265123,"remaining_time":0.512975715},
{"learn":[0.5655664579],"iteration":115,"passed_time":0.1546142964,"remaining_time":0.5118266365},
{"learn":[0.5650938886],"iteration":116,"passed_time":0.1560014363,"remaining_time":0.5106713683},
{"learn":[0.5647873899],"iteration":117,"passed_time":0.1574347745,"remaining_time":0.5096617277},
{"learn":[0.5644813128],"iteration":118,"passed_time":0.1588627621,"remaining_time":0.5086278351},
{"learn":[0.563858425],"iteration":119,"passed_time":0.1603244851,"remaining_time":0.5076942029},
{"learn":[0.5633321197],"iteration":120,"passed_time":0.1616777087,"remaining_time":0.5064119967},
{"learn":[0.562977138],"iteration":121,"passed_time":0.1632688328,"remaining_time":0.5058657277},
{"learn":[0.5626048078],"iteration":122,"passed_time":0.1647831318,"remaining_time":0.5050669975},
{"learn":[0.5620865681],"iteration":123,"passed_time":0.1662434537,"remaining_time":0.5040930532},
{"learn":[0.5613906829],"iteration":124,"passed_time":0.1676203661,"remaining_time":0.5028610983},
{"learn":[0.5611351208],"iteration":125,"passed_time":0.1692676949,"remaining_time":0.502429507},
{"learn":[0.5608487241],"iteration":126,"passed_time":0.1706954208,"remaining_time":0.5013337948},
{"learn":[0.5603352186],"iteration":127,"passed_time":0.1720900969,"remaining_time":0.5001368442},
{"learn":[0.5600576392],"iteration":128,"passed_time":0.1735538047,"remaining_time":0.4991353607},
{"learn":[0.5594620536],"iteration":129,"passed_time":0.1750494176,"remaining_time":0.4982175731},
{"learn":[0.55902132],"iteration":130,"passed_time":0.1767427487,"remaining_time":0.4978478951},
{"learn":[0.5587729678],"iteration":131,"passed_time":0.1781674316,"remaining_time":0.4967092032},
{"learn":[0.5581907664],"iteration":132,"passed_time":0.1795030422,"remaining_time":0.4953204248},
{"learn":[0.5576611009],"iteration":133,"passed_time":0.1808797833,"remaining_time":0.4940447813},
{"learn":[0.557398001],"iteration":134,"passed_time":0.1824198169,"remaining_time":0.4932091345},
{"learn":[0.5569724195],"iteration":135,"passed_time":0.1838467467,"remaining_time":0.4920604104},
{"learn":[0.5567825073],"iteration":136,"passed_time":0.1854040757,"remaining_time":0.4912531349},
{"learn":[0.5563426459],"iteration":137,"passed_time":0.1868280533,"remaining_time":0.4900851833},
{"learn":[0.5557807571],"iteration":138,"passed_time":0.1883326956,"remaining_time":0.4891230441},
{"learn":[0.5552331389],"iteration":139,"passed_time":0.1897495495,"remaining_time":0.4879274129},
{"learn":[0.5549043449],"iteration":140,"passed_time":0.1912951799,"remaining_time":0.4870565218},
{"learn":[0.5546103779],"iteration":141,"passed_time":0.1927318233,"remaining_time":0.4859013574},
{"learn":[0.5543151682],"iteration":142,"passed_time":0.1941710713,"remaining_time":0.4847487585},
{"learn":[0.5538872519],"iteration":143,"passed_time":0.1958280824,"remaining_time":0.484130537},
{"learn":[0.5534104542],"iteration":144,"passed_time":0.1972984556,"remaining_time":0.4830410464},
{"learn":[0.5529590085],"iteration":145,"passed_time":0.1986839473,"remaining_time":0.4817405298},
{"learn":[0.5525165872],"iteration":146,"passed_time":0.2001499012,"remaining_time":0.4806320757},
{"learn":[0.551894221],"iteration":147,"passed_time":0.2015947213,"remaining_time":0.4794685262},
{"learn":[0.5515028811],"iteration":148,"passed_time":0.2029449825,"remaining_time":0.4780784487},
{"learn":[0.551042639],"iteration":149,"passed_time":0.2045333051,"remaining_time":0.4772443786},
{"learn":[0.5507451089],"iteration":150,"passed_time":0.2059096633,"remaining_time":0.4759104139},
{"learn":[0.550201229],"iteration":151,"passed_time":0.2072286888,"remaining_time":0.4744446295},
{"learn":[0.5496930328],"iteration":152,"passed_time":0.2085571958,"remaining_time":0.4730022676},
{"learn":[0.5491419651],"iteration":153,"passed_time":0.2099168332,"remaining_time":0.4716313265},
{"learn":[0.5487370822],"iteration":154,"passed_time":0.2114280288,"remaining_time":0.4705978706},
{"learn":[0.5479874901],"iteration":155,"passed_time":0.2128341816,"remaining_time":0.4693266569},
{"learn":[0.5477726422],"iteration":156,"passed_time":0.2142022775,"remaining_time":0.4679705807},
{"learn":[0.5472518394],"iteration":157,"passed_time":0.2155810033,"remaining_time":0.4666373615},
{"learn":[0.5468215776],"iteration":158,"passed_time":0.2170206494,"remaining_time":0.4654342229},
{"learn":[0.5464266963],"iteration":159,"passed_time":0.2185352205,"remaining_time":0.4643873436},
{"learn":[0.5458351724],"iteration":160,"passed_time":0.2199255242,"remaining_time":0.4630729982},
{"learn":[0.5453699011],"iteration":161,"passed_time":0.2213502673,"remaining_time":0.4618295701},
{"learn":[0.5449492681],"iteration":162,"passed_time":0.2227148066,"remaining_time":0.4604594467},
{"learn":[0.5447057042],"iteration":163,"passed_time":0.2244254375,"remaining_time":0.4597984572},
{"learn":[0.5441684882],"iteration":164,"passed_time":0.2258147736,"remaining_time":0.4584724191},
{"learn":[0.5437541078],"iteration":165,"passed_time":0.2272327157,"remaining_time":0.4572031749},
{"learn":[0.5436541134],"iteration":166,"passed_time":0.2286392415,"remaining_time":0.4559093858},
{"learn":[0.5432457083],"iteration":167,"passed_time":0.2300483066,"remaining_time":0.4546192726},
{"learn":[0.5425813298],"iteration":168,"passed_time":0.2315422724,"remaining_time":0.4534940366},
{"learn":[0.5422432512],"iteration":169,"passed_time":0.2329507732,"remaining_time":0.4521985598},
{"learn":[0.5417895652],"iteration":170,"passed_time":0.2343124506,"remaining_time":0.450811674},
{"learn":[0.5414988912],"iteration":171,"passed_time":0.2357134143,"remaining_time":0.4494999993},
{"learn":[0.5410530303],"iteration":172,"passed_time":0.2371608543,"remaining_time":0.4482751409},
{"learn":[0.5408370348],"iteration":173,"passed_time":0.2386484418,"remaining_time":0.4471229427},
{"learn":[0.5405401266],"iteration":174,"passed_time":0.2399466199,"remaining_time":0.4456151513},
{"learn":[0.5400252025],"iteration":175,"passed_time":0.241310242,"remaining_time":0.4442302182},
{"learn":[0.5395519821],"iteration":176,"passed_time":0.2426201385,"remaining_time":0.4427474845},
{"learn":[0.5392077013],"iteration":177,"passed_time":0.2440642481,"remaining_time":0.4415094825},
{"learn":[0.5387429491],"iteration":178,"passed_time":0.2453869715,"remaining_time":0.4400514963},
{"learn":[0.5382232509],"iteration":179,"passed_time":0.2467144407,"remaining_time":0.4386034501},
{"learn":[0.5377501662],"iteration":180,"passed_time":0.2480764304,"remaining_time":0.4372175763},
{"learn":[0.5374500459],"iteration":181,"passed_time":0.2493973703,"remaining_time":0.4357602405},
{"learn":[0.5370052616],"iteration":182,"passed_time":0.2508815221,"remaining_time":0.4345871175},
{"learn":[0.5365628323],"iteration":183,"passed_time":0.2523209665,"remaining_time":0.4333338337},
{"learn":[0.5360773266],"iteration":184,"passed_time":0.253656033,"remaining_time":0.4319008129},
{"learn":[0.5356820664],"iteration":185,"passed_time":0.2549656474,"remaining_time":0.4304258779},
{"learn":[0.5353839351],"iteration":186,"passed_time":0.2562467769,"remaining_time":0.428905033},
{"learn":[0.5349943295],"iteration":187,"passed_time":0.2578150187,"remaining_time":0.4278632226},
{"learn":[0.5344564767],"iteration":188,"passed_time":0.2591572493,"remaining_time":0.4264439394},
{"learn":[0.5340325788],"iteration":189,"passed_time":0.2605275216,"remaining_time":0.4250712194},
{"learn":[0.53361342],"iteration":190,"passed_time":0.2618455495,"remaining_time":0.4236140042},
{"learn":[0.5333671713],"iteration":191,"passed_time":0.2632379387,"remaining_time":0.4222775267},
{"learn":[0.5330236953],"iteration":192,"passed_time":0.2647534521,"remaining_time":0.4211363201},
{"learn":[0.5327301546],"iteration":193,"passed_time":0.2661240318,"remaining_time":0.4197626481},
{"learn":[0.5321562987],"iteration":194,"passed_time":0.2674556322,"remaining_time":0.41832804},
{"learn":[0.5317619584],"iteration":195,"passed_time":0.2687819426,"remaining_time":0.4168862783},
{"learn":[0.5313732619],"iteration":196,"passed_time":0.2701753696,"remaining_time":0.4155489188},
{"learn":[0.5309757208],"iteration":197,"passed_time":0.2715899564,"remaining_time":0.4142432668},
{"learn":[0.5304979406],"iteration":198,"passed_time":0.2730188358,"remaining_time":0.4129581386},
{"learn":[0.5300566064],"iteration":199,"passed_time":0.2743526124,"remaining_time":0.4115289186},
{"learn":[0.5297958981],"iteration":200,"passed_time":0.2757515564,"remaining_time":0.4101975889},
{"learn":[0.5295039098],"iteration":201,"passed_time":0.277340967,"remaining_time":0.4091465751},
{"learn":[0.5291225348],"iteration":202,"passed_time":0.2787277648,"remaining_time":0.4077938233},
{"learn":[0.528710848],"iteration":203,"passed_time":0.280086217,"remaining_time":0.406399609},
{"learn":[0.5283668477],"iteration":204,"passed_time":0.2814847929,"remaining_time":0.4050634825},
{"learn":[0.5281205113],"iteration":205,"passed_time":0.2828012389,"remaining_time":0.4036095352},
{"learn":[0.5275140319],"iteration":206,"passed_time":0.2843596016,"remaining_time":0.4024993394},
{"learn":[0.5271069156],"iteration":207,"passed_time":0.2857909239,"remaining_time":0.4012064893},
{"learn":[0.5267116729],"iteration":208,"passed_time":0.2873095311,"remaining_time":0.4000338447},
{"learn":[0.5260819686],"iteration":209,"passed_time":0.2887206067,"remaining_time":0.3987094092},
{"learn":[0.5257142577],"iteration":210,"passed_time":0.2902030809,"remaining_time":0.397481945},
{"learn":[0.5253123067],"iteration":211,"passed_time":0.2916679169,"remaining_time":0.3962281135},
{"learn":[0.5249712743],"iteration":212,"passed_time":0.2930697574,"remaining_time":0.3948874196},
{"learn":[0.5245632581],"iteration":213,"passed_time":0.2944654415,"remaining_time":0.3935379265},
{"learn":[0.5241531485],"iteration":214,"passed_time":0.2958188263,"remaining_time":0.3921319325},
{"learn":[0.5235365494],"iteration":215,"passed_time":0.2972797171,"remaining_time":0.3908677762},
{"learn":[0.523330415],"iteration":216,"passed_time":0.2987813361,"remaining_time":0.3896549222},
{"learn":[0.5231457877],"iteration":217,"passed_time":0.3001069614,"remaining_time":0.3882117574},
{"learn":[0.5228403668],"iteration":218,"passed_time":0.3014415443,"remaining_time":0.3867811596},
{"learn":[0.5223002105],"iteration":219,"passed_time":0.3027896337,"remaining_time":0.3853686247},
{"learn":[0.522057581],"iteration":220,"passed_time":0.3042722888,"remaining_time":0.3841265547},
{"learn":[0.5217246286],"iteration":221,"passed_time":0.3055813894,"remaining_time":0.3826649831},
{"learn":[0.5213764672],"iteration":222,"passed_time":0.3069454904,"remaining_time":0.381273098},
{"learn":[0.5210792535],"iteration":223,"passed_time":0.3083468675,"remaining_time":0.3799273903},
{"learn":[0.5207406179],"iteration":224,"passed_time":0.3097059352,"remaining_time":0.3785294763},
{"learn":[0.5204011331],"iteration":225,"passed_time":0.3111307238,"remaining_time":0.3772115854},
{"learn":[0.5201730538],"iteration":226,"passed_time":0.3126536076,"remaining_time":0.3760107263},
{"learn":[0.5197523581],"iteration":227,"passed_time":0.3141134756,"remaining_time":0.3747318656},
{"learn":[0.5192921419],"iteration":228,"passed_time":0.3155441941,"remaining_time":0.3734169284},
{"learn":[0.5189301093],"iteration":229,"passed_time":0.3170244265,"remaining_time":0.3721591094},
{"learn":[0.5185563209],"iteration":230,"passed_time":0.3184678406,"remaining_time":0.3708564897},
{"learn":[0.5182203999],"iteration":231,"passed_time":0.3198343847,"remaining_time":0.3694638582},
{"learn":[0.5179244847],"iteration":232,"passed_time":0.321128885,"remaining_time":0.367988894},
{"learn":[0.5175501493],"iteration":233,"passed_time":0.3224955596,"remaining_time":0.3665975165},
{"learn":[0.5172860784],"iteration":234,"passed_time":0.3240556352,"remaining_time":0.3654244397},
{"learn":[0.5169347309],"iteration":235,"passed_time":0.3254509658,"remaining_time":0.3640637923},
{"learn":[0.5165460439],"iteration":236,"passed_time":0.3267776592,"remaining_time":0.3626266851},
{"learn":[0.5161300075],"iteration":237,"passed_time":0.3281395582,"remaining_time":0.3612292616},
{"learn":[0.5157039883],"iteration":238,"passed_time":0.3295065256,"remaining_time":0.3598376702},
{"learn":[0.5154735152],"iteration":239,"passed_time":0.3309331237,"remaining_time":0.358510884},
{"learn":[0.5151658744],"iteration":240,"passed_time":0.332379118,"remaining_time":0.3572041144},
{"learn":[0.5145513208],"iteration":241,"passed_time":0.3337289258,"remaining_time":0.3557936482},
{"learn":[0.5141010476],"iteration":242,"passed_time":0.3350600728,"remaining_time":0.3543639453},
{"learn":[0.5134471019],"iteration":243,"passed_time":0.3364361643,"remaining_time":0.3529822052},
{"learn":[0.5129787059],"iteration":244,"passed_time":0.3378915792,"remaining_time":0.3516830722},
{"learn":[0.5125607642],"iteration":245,"passed_time":0.3392471748,"remaining_time":0.3502796032},
{"learn":[0.5122953071],"iteration":246,"passed_time":0.3406629412,"remaining_time":0.3489381543},
{"learn":[0.5118778486],"iteration":247,"passed_time":0.3419933376,"remaining_time":0.3475093592},
{"learn":[0.5115531305],"iteration":248,"passed_time":0.3434202817,"remaining_time":0.3461786776},
{"learn":[0.5110573694],"iteration":249,"passed_time":0.3448454589,"remaining_time":0.3448454589},
{"learn":[0.5104578387],"iteration":250,"passed_time":0.3461620762,"remaining_time":0.3434038126},
{"learn":[0.5101699711],"iteration":251,"passed_time":0.3475080249,"remaining_time":0.3419920245},
{"learn":[0.5098297327],"iteration":252,"passed_time":0.3487764081,"remaining_time":0.3405050308},
{"learn":[0.509446062],"iteration":253,"passed_time":0.3503970048,"remaining_time":0.3393608787},
{"learn":[0.5089013083],"iteration":254,"passed_time":0.3518402881,"remaining_time":0.3380426298},
{"learn":[0.508537932],"iteration":255,"passed_time":0.3532466425,"remaining_time":0.3366882061},
{"learn":[0.5082750739],"iteration":256,"passed_time":0.3546362409,"remaining_time":0.3353175351},
{"learn":[0.5076857496],"iteration":257,"passed_time":0.3561037873,"remaining_time":0.3340198315},
{"learn":[0.5071140534],"iteration":258,"passed_time":0.3576665927,"remaining_time":0.332809455},
{"learn":[0.5066910043],"iteration":259,"passed_time":0.3590974722,"remaining_time":0.3314745897},
{"learn":[0.5061888874],"iteration":260,"passed_time":0.3604251026,"remaining_time":0.3300444426},
{"learn":[0.5057347865],"iteration":261,"passed_time":0.3618316587,"remaining_time":0.3286867739},
{"learn":[0.5052892933],"iteration":262,"passed_time":0.3632866605,"remaining_time":0.3273723898},
{"learn":[0.5049833356],"iteration":263,"passed_time":0.3647902691,"remaining_time":0.3261003921},
{"learn":[0.5047313247],"iteration":264,"passed_time":0.3661377594,"remaining_time":0.3246882017},
{"learn":[0.5044398486],"iteration":265,"passed_time":0.367571017,"remaining_time":0.3233519473},
{"learn":[0.5041834646],"iteration":266,"passed_time":0.3689112627,"remaining_time":0.3219337985},
{"learn":[0.503615014],"iteration":267,"passed_time":0.3705719189,"remaining_time":0.3207936015},
{"learn":[0.5030937984],"iteration":268,"passed_time":0.3719490987,"remaining_time":0.3194061034},
{"learn":[0.5026884672],"iteration":269,"passed_time":0.3733170633,"remaining_time":0.3180108317},
{"learn":[0.5022164582],"iteration":270,"passed_time":0.3746484924,"remaining_time":0.3165848884},
{"learn":[0.5018864123],"iteration":271,"passed_time":0.3760290476,"remaining_time":0.3152008193},
{"learn":[0.5015476102],"iteration":272,"passed_time":0.3775345606,"remaining_time":0.3139206786},
{"learn":[0.501252895],"iteration":273,"passed_time":0.3788662416,"remaining_time":0.3124955132},
{"learn":[0.5009977366],"iteration":274,"passed_time":0.3802206743,"remaining_time":0.3110896426},
{"learn":[0.5006104469],"iteration":275,"passed_time":0.3815739785,"remaining_time":0.309683229},
{"learn":[0.5000936683],"iteration":276,"passed_time":0.3829358071,"remaining_time":0.3082840613},
{"learn":[0.4996532412],"iteration":277,"passed_time":0.3843374058,"remaining_time":0.3069169211},
{"learn":[0.4994871978],"iteration":278,"passed_time":0.3857550052,"remaining_time":0.3055622084},
{"learn":[0.499014355],"iteration":279,"passed_time":0.3871021529,"remaining_time":0.3041516916},
{"learn":[0.498776518],"iteration":280,"passed_time":0.3884198081,"remaining_time":0.3027186405},
{"learn":[0.4982264709],"iteration":281,"passed_time":0.3897690818,"remaining_time":0.3013108505},
{"learn":[0.4980379125],"iteration":282,"passed_time":0.3911912706,"remaining_time":0.2999593841},
{"learn":[0.497777226],"iteration":283,"passed_time":0.3927456323,"remaining_time":0.2987079457},
{"learn":[0.4974991175],"iteration":284,"passed_time":0.3941338755,"remaining_time":0.297329064},
{"learn":[0.4971254327],"iteration":285,"passed_time":0.3954691986,"remaining_time":0.2959105193},
{"learn":[0.4965479892],"iteration":286,"passed_time":0.3969372241,"remaining_time":0.2945910409},
{"learn":[0.496364754],"iteration":287,"passed_time":0.3982488739,"remaining_time":0.293155421},
{"learn":[0.4959650804],"iteration":288,"passed_time":0.3995765898,"remaining_time":0.2917323891},
{"learn":[0.4954173709],"iteration":289,"passed_time":0.4009335366,"remaining_time":0.2903311817},
{"learn":[0.4951466416],"iteration":290,"passed_time":0.4022612073,"remaining_time":0.288909252},
{"learn":[0.4946701983],"iteration":291,"passed_time":0.4039402496,"remaining_time":0.28773826},
{"learn":[0.4942292414],"iteration":292,"passed_time":0.4053311679,"remaining_time":0.2863602449},
{"learn":[0.4938666821],"iteration":293,"passed_time":0.406738812,"remaining_time":0.2849938614},
{"learn":[0.493401656],"iteration":294,"passed_time":0.4081227678,"remaining_time":0.2836107369},
{"learn":[0.4930636052],"iteration":295,"passed_time":0.409584057,"remaining_time":0.2822809041},
{"learn":[0.492432027],"iteration":296,"passed_time":0.4110297182,"remaining_time":0.2809395044},
{"learn":[0.4918982514],"iteration":297,"passed_time":0.412429503,"remaining_time":0.2795663074},
{"learn":[0.4913395264],"iteration":298,"passed_time":0.4138646753,"remaining_time":0.2782167216},
{"learn":[0.4908331041],"iteration":299,"passed_time":0.4153274253,"remaining_time":0.2768849502},
{"learn":[0.490357806],"iteration":300,"passed_time":0.4169969263,"remaining_time":0.2756889978},
{"learn":[0.490069163],"iteration":301,"passed_time":0.4184553741,"remaining_time":0.2743515366},
{"learn":[0.4896150792],"iteration":302,"passed_time":0.4198263013,"remaining_time":0.2729563741},
{"learn":[0.489155519],"iteration":303,"passed_time":0.4212378145,"remaining_time":0.2715875383},
{"learn":[0.4887241404],"iteration":304,"passed_time":0.4226514745,"remaining_time":0.2702197952},
{"learn":[0.4881726897],"iteration":305,"passed_time":0.424163678,"remaining_time":0.2689142273},
{"learn":[0.4878127535],"iteration":306,"passed_time":0.4255565005,"remaining_time":0.2675322625},
{"learn":[0.4874909137],"iteration":307,"passed_time":0.4269215229,"remaining_time":0.2661328974},
{"learn":[0.4873271823],"iteration":308,"passed_time":0.4283634459,"remaining_time":0.2647812886},
{"learn":[0.486863791],"iteration":309,"passed_time":0.4299291935,"remaining_time":0.2635049896},
{"learn":[0.4864794557],"iteration":310,"passed_time":0.4314272503,"remaining_time":0.2621856923},
{"learn":[0.4862997962],"iteration":311,"passed_time":0.4328431469,"remaining_time":0.2608157424},
{"learn":[0.4859326502],"iteration":312,"passed_time":0.4342123309,"remaining_time":0.2594175907},
{"learn":[0.4855273076],"iteration":313,"passed_time":0.4356361574,"remaining_time":0.2580519913},
{"learn":[0.4851410483],"iteration":314,"passed_time":0.4374495942,"remaining_time":0.2569148411},
{"learn":[0.4846919431],"iteration":315,"passed_time":0.4391491319,"remaining_time":0.2557070895},
{"learn":[0.4842239897],"iteration":316,"passed_time":0.4406035797,"remaining_time":0.2543547479},
{"learn":[0.4838198008],"iteration":317,"passed_time":0.4420328775,"remaining_time":0.2529873701},
{"learn":[0.4834236111],"iteration":318,"passed_time":0.4436539731,"remaining_time":0.2517284299},
{"learn":[0.4827965294],"iteration":319,"passed_time":0.4451030499,"remaining_time":0.2503704656},
{"learn":[0.4825670721],"iteration":320,"passed_time":0.4464844358,"remaining_time":0.2489741869},
{"learn":[0.4821258328],"iteration":321,"passed_time":0.448016662,"remaining_time":0.2476613846},
{"learn":[0.481716448],"iteration":322,"passed_time":0.4495603957,"remaining_time":0.2463535296},
{"learn":[0.4814983882],"iteration":323,"passed_time":0.45097197,"remaining_time":0.2449724281},
{"learn":[0.4812502943],"iteration":324,"passed_time":0.4523096261,"remaining_time":0.2435513371},
{"learn":[0.4808686382],"iteration":325,"passed_time":0.4536963825,"remaining_time":0.2421569649},
{"learn":[0.4804257882],"iteration":326,"passed_time":0.4550352981,"remaining_time":0.240737329},
{"learn":[0.4801610804],"iteration":327,"passed_time":0.456674041,"remaining_time":0.2394754117},
{"learn":[0.47961954],"iteration":328,"passed_time":0.4580540674,"remaining_time":0.2380767341},
{"learn":[0.4792749432],"iteration":329,"passed_time":0.4594228585,"remaining_time":0.2366723816},
{"learn":[0.4788722401],"iteration":330,"passed_time":0.4606996653,"remaining_time":0.2352212793},
{"learn":[0.4785419336],"iteration":331,"passed_time":0.4620844974,"remaining_time":0.2338258903},
{"learn":[0.4781295614],"iteration":332,"passed_time":0.4636179666,"remaining_time":0.2325051064},
{"learn":[0.4778470592],"iteration":333,"passed_time":0.4651101789,"remaining_time":0.231162544},
{"learn":[0.4773593208],"iteration":334,"passed_time":0.4665024273,"remaining_time":0.2297698523},
{"learn":[0.4769915824],"iteration":335,"passed_time":0.4679264879,"remaining_time":0.2283926905},
{"learn":[0.4767567446],"iteration":336,"passed_time":0.4693492941,"remaining_time":0.2270146437},
{"learn":[0.4765659952],"iteration":337,"passed_time":0.4708558046,"remaining_time":0.2256764507},
{"learn":[0.4762041723],"iteration":338,"passed_time":0.47226091,"remaining_time":0.2242891047},
{"learn":[0.4759053076],"iteration":339,"passed_time":0.4736509109,"remaining_time":0.2228945463},
{"learn":[0.4754058537],"iteration":340,"passed_time":0.475109903,"remaining_time":0.2215321835},
{"learn":[0.474955667],"iteration":341,"passed_time":0.4767904872,"remaining_time":0.2202716286},
{"learn":[0.4745336093],"iteration":342,"passed_time":0.4783428967,"remaining_time":0.2189499556},
{"learn":[0.4741477287],"iteration":343,"passed_time":0.4800295065,"remaining_time":0.2176877995},
{"learn":[0.4737989192],"iteration":344,"passed_time":0.4815140112,"remaining_time":0.2163323819},
{"learn":[0.4733569793],"iteration":345,"passed_time":0.4832587596,"remaining_time":0.2150920491},
{"learn":[0.4732064706],"iteration":346,"passed_time":0.4847048038,"remaining_time":0.2137171037},
{"learn":[0.4725235634],"iteration":347,"passed_time":0.4865783644,"remaining_time":0.212528481},
{"learn":[0.471900883],"iteration":348,"passed_time":0.4882479661,"remaining_time":0.2112476873},
{"learn":[0.4714845947],"iteration":349,"passed_time":0.4899047607,"remaining_time":0.2099591831},
{"learn":[0.4711843923],"iteration":350,"passed_time":0.4915129187,"remaining_time":0.2086479341},
{"learn":[0.4706250721],"iteration":351,"passed_time":0.4931172777,"remaining_time":0.2073334009},
{"learn":[0.4703616083],"iteration":352,"passed_time":0.4945920786,"remaining_time":0.2059632735},
{"learn":[0.4699817342],"iteration":353,"passed_time":0.496322449,"remaining_time":0.2046979592},
{"learn":[0.469640557],"iteration":354,"passed_time":0.4979710115,"remaining_time":0.2033966103},
{"learn":[0.4691427525],"iteration":355,"passed_time":0.4993683684,"remaining_time":0.2019916996},
{"learn":[0.4686747656],"iteration":356,"passed_time":0.5008558455,"remaining_time":0.2006229297},
{"learn":[0.4680280196],"iteration":357,"passed_time":0.50233638,"remaining_time":0.1992507429},
{"learn":[0.4676777965],"iteration":358,"passed_time":0.5039630273,"remaining_time":0.1979353394},
{"learn":[0.4675155684],"iteration":359,"passed_time":0.505464661,"remaining_time":0.1965695904},
{"learn":[0.4671065541],"iteration":360,"passed_time":0.5068703707,"remaining_time":0.1951661538},
{"learn":[0.4669432914],"iteration":361,"passed_time":0.5083036183,"remaining_time":0.1937732026},
{"learn":[0.4665594472],"iteration":362,"passed_time":0.5098290116,"remaining_time":0.192414806},
{"learn":[0.4661164126],"iteration":363,"passed_time":0.5112841692,"remaining_time":0.19102925},
{"learn":[0.4657757829],"iteration":364,"passed_time":0.5127332162,"remaining_time":0.1896410526},
{"learn":[0.465603168],"iteration":365,"passed_time":0.5140375911,"remaining_time":0.1881995552},
{"learn":[0.4653501352],"iteration":366,"passed_time":0.5154858468,"remaining_time":0.1868109472},
{"learn":[0.4648209944],"iteration":367,"passed_time":0.5172974098,"remaining_time":0.1855523318},
{"learn":[0.4645318323],"iteration":368,"passed_time":0.5186721682,"remaining_time":0.1841356478},
{"learn":[0.4641028002],"iteration":369,"passed_time":0.5200663409,"remaining_time":0.1827260117},
{"learn":[0.4636967109],"iteration":370,"passed_time":0.5214852197,"remaining_time":0.1813250494},
{"learn":[0.46337409],"iteration":371,"passed_time":0.5229879166,"remaining_time":0.1799528315},
{"learn":[0.4629580281],"iteration":372,"passed_time":0.5244948805,"remaining_time":0.1785813668},
{"learn":[0.4625998403],"iteration":373,"passed_time":0.5258427537,"remaining_time":0.1771555801},
{"learn":[0.4622704459],"iteration":374,"passed_time":0.5271345134,"remaining_time":0.1757115045},
{"learn":[0.4619358585],"iteration":375,"passed_time":0.5284534782,"remaining_time":0.1742772109},
{"learn":[0.4614166818],"iteration":376,"passed_time":0.5299677374,"remaining_time":0.1729072459},
{"learn":[0.4609663125],"iteration":377,"passed_time":0.5313674822,"remaining_time":0.1714995577},
{"learn":[0.4605959047],"iteration":378,"passed_time":0.5327018131,"remaining_time":0.1700710274},
{"learn":[0.4600504196],"iteration":379,"passed_time":0.5340299171,"remaining_time":0.1686410265},
{"learn":[0.4596409264],"iteration":380,"passed_time":0.5354492595,"remaining_time":0.1672400574},
{"learn":[0.4594717986],"iteration":381,"passed_time":0.5369302577,"remaining_time":0.1658580377},
{"learn":[0.458938062],"iteration":382,"passed_time":0.5383284102,"remaining_time":0.1644501932},
{"learn":[0.4584798236],"iteration":383,"passed_time":0.5396548818,"remaining_time":0.1630207456},
{"learn":[0.4580325622],"iteration":384,"passed_time":0.5409634987,"remaining_time":0.1615864996},
{"learn":[0.4575400618],"iteration":385,"passed_time":0.5424751382,"remaining_time":0.1602128647},
{"learn":[0.4571822406],"iteration":386,"passed_time":0.5439777594,"remaining_time":0.1588358832},
{"learn":[0.4567365373],"iteration":387,"passed_time":0.5453638511,"remaining_time":0.1574246168},
{"learn":[0.4564084824],"iteration":388,"passed_time":0.5466703822,"remaining_time":0.1559907774},
{"learn":[0.4561824374],"iteration":389,"passed_time":0.5480018919,"remaining_time":0.1545646362},
{"learn":[0.4558490002],"iteration":390,"passed_time":0.5494640973,"remaining_time":0.1531754133},
{"learn":[0.4555050518],"iteration":391,"passed_time":0.5509913146,"remaining_time":0.1518037295},
{"learn":[0.4552563474],"iteration":392,"passed_time":0.5523452334,"remaining_time":0.1503840712},
{"learn":[0.4548273894],"iteration":393,"passed_time":0.5537086039,"remaining_time":0.1489672894},
{"learn":[0.454390517],"iteration":394,"passed_time":0.555012847,"remaining_time":0.1475350606},
{"learn":[0.4540943142],"iteration":395,"passed_time":0.5564621767,"remaining_time":0.1461415818},
{"learn":[0.453865643],"iteration":396,"passed_time":0.5577844769,"remaining_time":0.1447148643},
{"learn":[0.4532187148],"iteration":397,"passed_time":0.5590524672,"remaining_time":0.1432747529},
{"learn":[0.4528956657],"iteration":398,"passed_time":0.5603297879,"remaining_time":0.1418378661},
{"learn":[0.4522924322],"iteration":399,"passed_time":0.5616668386,"remaining_time":0.1404167097},
{"learn":[0.4519519357],"iteration":400,"passed_time":0.5630428134,"remaining_time":0.1390055824},
{"learn":[0.4515081047],"iteration":401,"passed_time":0.5644178622,"remaining_time":0.1375944042},
{"learn":[0.4512429278],"iteration":402,"passed_time":0.5656834947,"remaining_time":0.1361570694},
{"learn":[0.4508672801],"iteration":403,"passed_time":0.5670337461,"remaining_time":0.1347406921},
{"learn":[0.4505997822],"iteration":404,"passed_time":0.5682887783,"remaining_time":0.133302306},
{"learn":[0.4501902174],"iteration":405,"passed_time":0.569669247,"remaining_time":0.1318938651},
{"learn":[0.4498653949],"iteration":406,"passed_time":0.5709930183,"remaining_time":0.1304726062},
{"learn":[0.4496577572],"iteration":407,"passed_time":0.5722299945,"remaining_time":0.1290322537},
{"learn":[0.449371488],"iteration":408,"passed_time":0.5734815608,"remaining_time":0.1275961419},
{"learn":[0.4489812686],"iteration":409,"passed_time":0.5747317568,"remaining_time":0.1261606295},
{"learn":[0.4486282176],"iteration":410,"passed_time":0.5761377192,"remaining_time":0.1247597494},
{"learn":[0.4482333652],"iteration":411,"passed_time":0.577458115,"remaining_time":0.1233405683},
{"learn":[0.4478903319],"iteration":412,"passed_time":0.5787154549,"remaining_time":0.1219085825},
{"learn":[0.4475106795],"iteration":413,"passed_time":0.5799727142,"remaining_time":0.1204774237},
{"learn":[0.4471141081],"iteration":414,"passed_time":0.5812203005,"remaining_time":0.1190451218},
{"learn":[0.4468124919],"iteration":415,"passed_time":0.5825487966,"remaining_time":0.1176300455},
{"learn":[0.4466117545],"iteration":416,"passed_time":0.5839238054,"remaining_time":0.1162246423},
{"learn":[0.4463038041],"iteration":417,"passed_time":0.5851876444,"remaining_time":0.1147975762},
{"learn":[0.4457207707],"iteration":418,"passed_time":0.586447604,"remaining_time":0.1133705392},
{"learn":[0.44526544],"iteration":419,"passed_time":0.5876968126,"remaining_time":0.11194225},
{"learn":[0.4448789935],"iteration":420,"passed_time":0.5890615825,"remaining_time":0.1105364965},
{"learn":[0.4444979194],"iteration":421,"passed_time":0.5904083473,"remaining_time":0.1091276092},
{"learn":[0.4440497259],"iteration":422,"passed_time":0.5918108232,"remaining_time":0.1077291569},
{"learn":[0.443816654],"iteration":423,"passed_time":0.5930507214,"remaining_time":0.1063015444},
{"learn":[0.4435630189],"iteration":424,"passed_time":0.5943066104,"remaining_time":0.1048776371},
{"learn":[0.4431890052],"iteration":425,"passed_time":0.5956818294,"remaining_time":0.1034752474},
{"learn":[0.4426170568],"iteration":426,"passed_time":0.5969712817,"remaining_time":0.1020583222},
{"learn":[0.4423147432],"iteration":427,"passed_time":0.5982466779,"remaining_time":0.1006396281},
{"learn":[0.4419340997],"iteration":428,"passed_time":0.5995141039,"remaining_time":0.09922028293},
{"learn":[0.4414686978],"iteration":429,"passed_time":0.6007530248,"remaining_time":0.09779700403},
{"learn":[0.4411847151],"iteration":430,"passed_time":0.6021314393,"remaining_time":0.09639691255},
{"learn":[0.4409845375],"iteration":431,"passed_time":0.6034134352,"remaining_time":0.09498174444},
{"learn":[0.4405687172],"iteration":432,"passed_time":0.6046627445,"remaining_time":0.09356213368},
{"learn":[0.4402320758],"iteration":433,"passed_time":0.6059091519,"remaining_time":0.09214286642},
{"learn":[0.439894993],"iteration":434,"passed_time":0.6071380874,"remaining_time":0.09072178317},
{"learn":[0.4394664768],"iteration":435,"passed_time":0.6084198919,"remaining_time":0.08930934194},
{"learn":[0.4391106244],"iteration":436,"passed_time":0.6097627976,"remaining_time":0.08790630721},
{"learn":[0.4387607157],"iteration":437,"passed_time":0.611035967,"remaining_time":0.0864936757},
{"learn":[0.43842186],"iteration":438,"passed_time":0.6122826061,"remaining_time":0.08507799311},
{"learn":[0.4381675584],"iteration":439,"passed_time":0.6135310287,"remaining_time":0.0836633221},
{"learn":[0.437825024],"iteration":440,"passed_time":0.6147818494,"remaining_time":0.08224972589},
{"learn":[0.4374174748],"iteration":441,"passed_time":0.6161782587,"remaining_time":0.0808559706},
{"learn":[0.4370292166],"iteration":442,"passed_time":0.6174562243,"remaining_time":0.07944696339},
{"learn":[0.4367263368],"iteration":443,"passed_time":0.6187179271,"remaining_time":0.07803649531},
{"learn":[0.4363820875],"iteration":444,"passed_time":0.6199724759,"remaining_time":0.07662581163},
{"learn":[0.4360356531],"iteration":445,"passed_time":0.6212240825,"remaining_time":0.07521547187},
{"learn":[0.4356518692],"iteration":446,"passed_time":0.6225717948,"remaining_time":0.07381723741},
{"learn":[0.435334419],"iteration":447,"passed_time":0.6238949313,"remaining_time":0.07241637595},
{"learn":[0.4348998579],"iteration":448,"passed_time":0.6251745694,"remaining_time":0.07101091991},
{"learn":[0.4345280337],"iteration":449,"passed_time":0.6264241105,"remaining_time":0.06960267894},
{"learn":[0.4340468539],"iteration":450,"passed_time":0.6276759589,"remaining_time":0.06819539243},
{"learn":[0.4337300011],"iteration":451,"passed_time":0.6291360085,"remaining_time":0.06681090356},
{"learn":[0.4333745552],"iteration":452,"passed_time":0.6303953032,"remaining_time":0.0654052522},
{"learn":[0.4330336907],"iteration":453,"passed_time":0.6316445419,"remaining_time":0.06399922671},
{"learn":[0.4326222287],"iteration":454,"passed_time":0.6329130864,"remaining_time":0.06259579975},
{"learn":[0.4322023127],"iteration":455,"passed_time":0.634153559,"remaining_time":0.06119025569},
{"learn":[0.4318564773],"iteration":456,"passed_time":0.6355487596,"remaining_time":0.0597999927},
{"learn":[0.4313848657],"iteration":457,"passed_time":0.6368618805,"remaining_time":0.05840218118},
{"learn":[0.4308193855],"iteration":458,"passed_time":0.6381440579,"remaining_time":0.05700197467},
{"learn":[0.4304367897],"iteration":459,"passed_time":0.6394011056,"remaining_time":0.05560009614},
{"learn":[0.4300369305],"iteration":460,"passed_time":0.6406559768,"remaining_time":0.05419866181},
{"learn":[0.4296499064],"iteration":461,"passed_time":0.6419629413,"remaining_time":0.05280214668},
{"learn":[0.4292752812],"iteration":462,"passed_time":0.6432625099,"remaining_time":0.05140542735},
{"learn":[0.4289472239],"iteration":463,"passed_time":0.6445163937,"remaining_time":0.05000558227},
{"learn":[0.4285664647],"iteration":464,"passed_time":0.6457627305,"remaining_time":0.04860579692},
{"learn":[0.428247497],"iteration":465,"passed_time":0.6469999485,"remaining_time":0.04720600483},
{"learn":[0.4279174589],"iteration":466,"passed_time":0.6482739844,"remaining_time":0.04580951068},
{"learn":[0.427327089],"iteration":467,"passed_time":0.6496400046,"remaining_time":0.04441982938},
{"learn":[0.427202182],"iteration":468,"passed_time":0.6508957323,"remaining_time":0.04302295885},
{"learn":[0.4267873304],"iteration":469,"passed_time":0.6521494852,"remaining_time":0.04162656288},
{"learn":[0.4265264026],"iteration":470,"passed_time":0.6534056058,"remaining_time":0.04023091841},
{"learn":[0.4261920363],"iteration":471,"passed_time":0.6546493531,"remaining_time":0.03883513112},
{"learn":[0.4259360403],"iteration":472,"passed_time":0.6560113429,"remaining_time":0.03744673627},
{"learn":[0.4255562923],"iteration":473,"passed_time":0.6572735898,"remaining_time":0.03605298172},
{"learn":[0.4250843424],"iteration":474,"passed_time":0.6585327736,"remaining_time":0.03465961966},
{"learn":[0.4248771382],"iteration":475,"passed_time":0.6597732865,"remaining_time":0.03326587999},
{"learn":[0.424523669],"iteration":476,"passed_time":0.6610199055,"remaining_time":0.0318730772},
{"learn":[0.4242624959],"iteration":477,"passed_time":0.6623757178,"remaining_time":0.0304859117},
{"learn":[0.4238610853],"iteration":478,"passed_time":0.6636660266,"remaining_time":0.02909600534},
{"learn":[0.4235978823],"iteration":479,"passed_time":0.6649198096,"remaining_time":0.02770499207},
{"learn":[0.4233581675],"iteration":480,"passed_time":0.666185825,"remaining_time":0.02631503259},
{"learn":[0.4230790424],"iteration":481,"passed_time":0.6674399808,"remaining_time":0.02492514451},
{"learn":[0.4228192146],"iteration":482,"passed_time":0.6687765084,"remaining_time":0.02353871769},
{"learn":[0.4225272681],"iteration":483,"passed_time":0.6700895996,"remaining_time":0.0221517223},
{"learn":[0.4220721958],"iteration":484,"passed_time":0.6713386167,"remaining_time":0.02076305},
{"learn":[0.4216818319],"iteration":485,"passed_time":0.6725853969,"remaining_time":0.01937488798},
{"learn":[0.4212710384],"iteration":486,"passed_time":0.6738415176,"remaining_time":0.01798755591},
{"learn":[0.421010723],"iteration":487,"passed_time":0.6751818239,"remaining_time":0.01660283174},
{"learn":[0.4205174431],"iteration":488,"passed_time":0.6765936697,"remaining_time":0.0152198985},
{"learn":[0.4200962257],"iteration":489,"passed_time":0.6778718166,"remaining_time":0.01383411871},
{"learn":[0.4194316398],"iteration":490,"passed_time":0.6791561805,"remaining_time":0.01244889129},
{"learn":[0.4190926643],"iteration":491,"passed_time":0.6804142861,"remaining_time":0.01106364693},
{"learn":[0.4187010343],"iteration":492,"passed_time":0.6817890929,"remaining_time":0.009680575355},
{"learn":[0.4183777413],"iteration":493,"passed_time":0.6833569255,"remaining_time":0.008299881686},
{"learn":[0.4179331528],"iteration":494,"passed_time":0.6847503933,"remaining_time":0.00691667064},
{"learn":[0.4177224546],"iteration":495,"passed_time":0.6861048154,"remaining_time":0.00553310335},
{"learn":[0.4172676302],"iteration":496,"passed_time":0.6873937236,"remaining_time":0.004149257889},
{"learn":[0.4169742871],"iteration":497,"passed_time":0.6887117926,"remaining_time":0.002765910814},
{"learn":[0.4164337121],"iteration":498,"passed_time":0.6900559175,"remaining_time":0.00138287759},
{"learn":[0.4160051994],"iteration":499,"passed_time":0.6914751493,"remaining_time":0}
]}